olca/__init__.py
olca/fusewill_cli.py
olca/fusewill_utils.py
olca/oiv.py
olca/olcacli.py
olca/olcahelper.py
olca/prompts.py
olca/tracing.py
olca/utils.py
olca-0.2.88.dist-info/licenses/LICENSE
olca-0.2.88.dist-info/METADATA
olca-0.2.88.dist-info/WHEEL
olca-0.2.88.dist-info/entry_points.txt
olca-0.2.88.dist-info/top_level.txt
olca-0.2.88.dist-info/RECORD
