Metadata-Version: 2.4
Name: olca
Version: 0.2.88
Summary: A Python package for experimental usage of Langchain and Human-in-the-Loop
Home-page: https://github.com/jgwill/olca
Author: Jean GUillaume ISabelle
Author-email: Jean GUillaume ISabelle <jgi@jgwill.com>
License:                     GNU GENERAL PUBLIC LICENSE
Classifier: Programming Language :: Python :: 3
Classifier: License :: OSI Approved :: MIT License
Classifier: Operating System :: OS Independent
Requires-Python: >=3.6
License-File: LICENSE
Requires-Dist: boto3
Requires-Dist: mutagen
Requires-Dist: certifi
Requires-Dist: charset-normalizer
Requires-Dist: idna
Requires-Dist: redis
Requires-Dist: requests
Requires-Dist: markdown
Requires-Dist: langchain
Requires-Dist: langchain-openai
Requires-Dist: langchain-ollama
Requires-Dist: langchain-experimental
Requires-Dist: click
Requires-Dist: langgraph
Requires-Dist: langfuse
Requires-Dist: pytz
Requires-Dist: google.generativeai
Requires-Dist: arxiv
Requires-Dist: tlid
Dynamic: author
Dynamic: home-page
Dynamic: license-file
Dynamic: requires-python
